{
  "kind": "collectionType",
  "collectionName": "orders",
  "info": {
    "name": "order"
  },
  "options": {
    "increments": true,
    "timestamps": true,
    "draftAndPublish": true
  },
  "pluginOptions": {},
  "attributes": {
    "name": {
      "type": "string",
      "required": true,
      "unique": true
    },
    "description": {
      "type": "richtext",
      "required": true
    },
    "image": {
      "collection": "file",
      "via": "related",
      "allowedTypes": [
        "files",
        "images",
        "videos"
      ],
      "plugin": "upload",
      "required": true,
      "pluginOptions": {}
    },
    "categoris": {
      "via": "restorant11",
      "collection": "categori"
    }
  }
}
